<?xml version="1.0" ?><contentList date="26/10/2020 01:10">
  <content contentuid="h00b31d14gdb9bg4beegb736g7c0651dda571" version="2">Sou muito melhor que mágico: sou feiticeira.</content>
  <content contentuid="h09182816ge832g49f0g8e33g1d3e23737c40" version="1">A vida na natureza foi o que me fez um guerreiro.</content>
  <content contentuid="h093c4b7bg2d8ag4fb9ga3bfgbe111ed44c4e" version="2">Esperava que os Zhentarim honrassem um companheiro banite.</content>
  <content contentuid="h09b18d41g7bc3g4ff9g9596gb8e97b2d7d00" version="1">Um aviso, chefe: não fique entre mim e minha vingança.</content>
  <content contentuid="h09e6f6ddg6001g4d20ga341g28c1f894d1b5" version="3">Eu te ofereço algo melhor... Sou um de seus discípulos.</content>
  <content contentuid="h0a48545age79cg4e92ga6b6g191d1a9cafb7" version="3">Não há mais esperança para nós, então?</content>
  <content contentuid="h0c569e8eg6612g4c09ga5c2gd9e76573d20b" version="1">Um aviso, chefe: não fique entre mim e minha vingança.</content>
  <content contentuid="h20432a12g3991g4c3fg8050g89702fcc2eb5" version="1">Okey. Eu estou pronto.</content>
  <content contentuid="h22825f34g8b33g4e49ga6f6gc79a88f96da0" version="2">Você ainda tem essa poção? Eu estou pronto.</content>
  <content contentuid="h250d6bb5ga940g404fgb668g683bee263971" version="1">Eu nunca pensaria nisso! Você é um pouco paranoico, não é?</content>
  <content contentuid="h26fbd0bag75e9g4085g9bf7ge24498063711" version="2">Não sou criminoso. Eu vi que a fechadura estava danificada e pretendia lançar um feitiço para consertá-lo.</content>
  <content contentuid="h2b98f58fg8967g46fbg93d2g9a48134d7372" version="2">Sou um grande guerreiro. Você realmente quer jogar em uma luta?</content>
  <content contentuid="h2c825618g2cb3g4156gac06g32e333dd5a55" version="2">É claro. Pareço amaldiçoado?</content>
  <content contentuid="h2d89f247g547ag4056gbed9g09ac52c5ec34" version="3">Eu te ofereço algo melhor... Sou um dos discípulos do Absoluto.</content>
  <content contentuid="h2ed24e1fgec45g447agb8c2g20d2369c2c6c" version="1">Sou muito melhor que mágico: sou uma bruxa.</content>
  <content contentuid="h2f956eb7g4829g4954gb20egd6afc2c5fb14" version="2">Você parece surpreendentemente calmo. Minha aparência geralmente causa uma reação mais forte.</content>
  <content contentuid="h2fb4be6ag47f2g4612gb2d2g7e7333dbbb13" version="1">Saber que eu tinha um verme dentro de mim era algo que estava me deixando louco. Perguntei-lhe como ele podia lidar com isso.</content>
  <content contentuid="h33678b68g1d80g41afgbdd1g0202dea92b3e" version="2">Eu gostaria de me ver como a escolhida de Shar, com todo o seu poder à minha disposição.</content>
  <content contentuid="h340d64c3ge526g4f6bga9eagccb4fad630c8" version="1">Ainda não estou pronto para me livrar de um artefato.</content>
  <content contentuid="h35adb0acg5f9ag4640g8659g971ccbb19166" version="4">Você vai dizer, eu sou todo ouvidos.</content>
  <content contentuid="h35fd9ed1gd7bag4628gb00ag2483aa2e3235" version="1">Que a verdade e a justiça estejam com você, irmão. Sou a cleriga do Tyr.</content>
  <content contentuid="h39b7a55agedafg4c47g88f8gf0c970375ea2" version="4">Você terá que encontrar outra pessoa para a missão.</content>
  <content contentuid="h39fb14c8gc40ag4800gb213g22f0be7a7d42" version="3">Devemos nos concentrar em sobreviver à nossa disjunção... Juntos.</content>
  <content contentuid="h3c672912g0f8eg4557g9c14gc2b1827fdee9" version="3">Eles me prenderam, assim como você.</content>
  <content contentuid="h4196c7e5gedbag4a75ga657g92553fe5d622" version="1">Você não é nem um duende nem um ogro. Você deveria ir embora. Lugar ruim.</content>
  <content contentuid="h43a90bddg221fg4eb4g93cbge65b60b34279" version="2">Posso ser seu amigo ou seu inimigo. Você decide.</content>
  <content contentuid="h46852b29g4627g4b62ga21eg5fa716715d99" version="4">Eu disse que era tudo bobagem, que tínhamos problemas reais para lidar acordado.</content>
  <content contentuid="h46d2a305g0601g493bg97f3g692e8c62c5ae" version="1">Você cometeu um erro. Isso não te faz mais fraco. Isso faz de você muito humano. Literalmente.</content>
  <content contentuid="h49420729g32acg4d86g999eg227f1da9643a" version="2">Muito bem. Vamos viajar juntos.</content>
  <content contentuid="h4d5a9463g8cb5g468eg8264g4127b600dbe9" version="2">Sou um grande guerreiro. Você realmente quer jogar em uma luta?</content>
  <content contentuid="h4dc1b7ccg4240g4cccga34egfb78cebaf2ff" version="1">Sou um viajante em busca de aventura.</content>
  <content contentuid="h4dcd6661g7c81g464cgb246g58826f931527" version="3">Eu disse que não tinha medo, que me sentia poderoso.</content>
  <content contentuid="h4de34462ge936g4e30g8f95g52bdf3712679" version="5">Eu vi um homem. Ele me chamou de &quot;escolhido&quot;... E ele me curou.</content>
  <content contentuid="h4f8f45f6g78fag489eg8a7dgc468ddc3b055" version="2">Você primeiro! Não quero ser rude.</content>
  <content contentuid="h5554d20dg2737g48bagaa48g5fb6113d1299" version="2">Não sou seu inimigo. Eu venho em paz.</content>
  <content contentuid="h57cbb83cge823g4677g83d2g14d0897cbfcd" version="2">Não precisa se preocupar. Não sou vampiro e Astarion está morto.</content>
  <content contentuid="h585b86abgcbeeg4684g9dbbg7b9050a375aa" version="3">Não, mas os traficantes acham que sou um deles.</content>
  <content contentuid="h5b1e4ec0gb289g4eb6g9010g163baea2a44f" version="2">Não sou Elminster, mas me viro muito bem.</content>
  <content contentuid="h5c15047dg0e5ag4ca1gb2a2g45a4dec1d3d1" version="2">Não precisa se preocupar. Não sou vampiro e Astarion está fora daqui.</content>
  <content contentuid="h5df63514g245ag48bdgafdbg946b386bdafb" version="2">&lt;i&gt;afirmar que você é uma pessoa de grande importância. Você pode se tornar um refém valioso... ou um possível aliado, &lt;/i&gt;</content>
  <content contentuid="h6275d7e2gf9a2g4e65ga639g1081b0557b90" version="1">Sou muito melhor que mágico: sou uma bruxa.</content>
  <content contentuid="h6537ffacg4070g4a3bg837age217877d5750" version="3">Estamos nisso juntos.</content>
  <content contentuid="h65f2b252gea47g4e2dg8f21gfa8a3b24d0f3" version="3">Tenho certeza que há uma maneira de trabalharmos juntos.</content>
  <content contentuid="h676ce5edgdd6fg4ee9ga981g2ea020239bd1" version="1">Leva muitos anos de disciplina para treinar o campeão na sua frente.</content>
  <content contentuid="h690bdc1fge808g4d42g8ae2g3a7e8e94a889" version="6">Tenho certeza que sou mais rico que um duende.</content>
  <content contentuid="h6d7311b0ga9d4g4477ga244g733f4005b560" version="1">&lt;i&gt;&lt;/i&gt;. Espero que seja capim-corvo, &lt;i&gt;zurgnak&lt;/i&gt; malnacide!</content>
  <content contentuid="h6dba94a4gd3eag4cafg821fg636c4c8cf716" version="3">A verdade é que estou pronto para matá-lo.</content>
  <content contentuid="h6eadc67eg323fg4aa0gb520g71a9c245e2bb" version="2">Sou um viajante em busca de aventura.</content>
  <content contentuid="h74033cb3ged3ag4754g991dgaaacc668c99f" version="2">&lt;i&gt;na mistura de prazer e dor. Você nunca se sentiu tão vivo, &lt;/i&gt;</content>
  <content contentuid="h765b7b2bge11cg4f32g950fgd4b94d706369" version="2">Eu estou pronto. O bosque cairá.</content>
  <content contentuid="h777acc50gbafbg4dbdgbda4ge64b04b6d766" version="3">Sim, sou um aliado! Conheço seu mestre. Somos aliados.</content>
  <content contentuid="h77f18561g7c1dg4d92gb451g521600ffed36" version="1">Minha oferta ainda está de pé. Vamos viajar juntos.</content>
  <content contentuid="h79365ebag0402g40bcg987bg18c0e195597d" version="1">Sou um mercenário. Estou aqui para falar com meu chefe. Afaste-se imediatamente.</content>
  <content contentuid="h7946da47ge443g4fd1g8808ga8dbaf270dca" version="3">Eu gostaria de uma canção sobre o meu legado mestiço. Estou tão orgulhosa dele.</content>
  <content contentuid="h7bcade0cgd3e3g44feg8326gbee915848d8c" version="2">Deveríamos viajar juntos.</content>
  <content contentuid="h7da80f90g3f77g4baeg8b07g88708ef50945" version="5">A coisa sensata a fazer seria ficarmos juntos. O sindicato faz a força.</content>
  <content contentuid="h7f58cf80g9e3ag4c30g8aeagea1c24f40d66" version="2">&lt;i&gt; olha o rothé direto para o olho. Mostre a ela como você está calmo... e quão calma a besta poderia ser, &lt;/i&gt;</content>
  <content contentuid="h85d0c8a9g741bg43f5gb8b1gb38a20427af4" version="2">A Ceremorfosis? Eu sou todo ouvidos.</content>
  <content contentuid="h8ad4ae47g3a90g45f2gbeefg64bfb898b3f8" version="2">Tenho certeza que há uma maneira de trabalharmos todos juntos.</content>
  <content contentuid="h8c0fa000g7d85g4238g8241g46c52b80c60e" version="2">Bem, a verdade é que sou um mágico.</content>
  <content contentuid="h8f0c55d8g3d2fg44edga12eg215ece05b148" version="2">Ainda não estou pronto para me livrar de um artefato.</content>
  <content contentuid="h921d9db0g33f2g46b8gb884g806cb31b8fd6" version="1">Como assim, elfo? Eu gesticuly: Eu estava &lt;i&gt;githyanki&lt;/i&gt;.*</content>
  <content contentuid="h95ada7d4g386eg4a44ga96cg4184103764e5" version="1">Eu sou um. Estou aqui para ver Minthara.</content>
  <content contentuid="h970af8eegfc32g4695g9f0ag8f29b917271d" version="2">Sou um grande guerreiro. Você realmente quer jogar em uma luta?</content>
  <content contentuid="h979ea3b8g658fg465aga55fg65946cf750f3" version="3">Então, você foi enganado? Eu não o teria deixado correr... Eu teria ficado furioso.</content>
  <content contentuid="h98d51a01gb096g4b07gbfc4gc76ecf21bea6" version="3">Só estou tentando ser educado, só isso.</content>
  <content contentuid="ha2ea355fg1683g4b24gb1fbg41cf99ecc760" version="2">Você quer desprezar um guerreiro cigano?</content>
  <content contentuid="ha3aef3e0g8f59g4360g887bg91a4a4878f64" version="3">*Eu admiti que não estava muito orgulhoso de nossas ações.*</content>
  <content contentuid="ha3f2770fg7468g4368gaf8eg3b61ac35c21e" version="1">O que te faz pensar que sou elfo?</content>
  <content contentuid="ha95a2612g08ccg4dccg90a9g547c9691d43c" version="3">Um cadáver não tem utilidade, mas um informante vivo ainda pode descobrir algo.</content>
  <content contentuid="ha9ae14a5gc3c3g42e6g9c93gf90870c2d352" version="2">Sem essa. Tenho certeza que um colega druida pode saber.</content>
  <content contentuid="hab87ebfag4e0eg4068g9aaegc5215dde72f4" version="2">Ninguém além de mim. Só estou tentando sobreviver.</content>
  <content contentuid="hae574aa4gdc6cg4a64g8f94gaf65a964226d" version="4">Passe-me o lau. Podemos jogar juntos.</content>
  <content contentuid="hb2930db4gaf7cg4a9bgbf1cg6a077276960a" version="2">O Senhor te abençoe. Sou um clériga da igreja de Tyr.</content>
  <content contentuid="hb361b923g4cc2g4f51gb293gaf2412b0c3ff" version="1">Não se preocupe. Seja o que for, estamos nisso juntos.</content>
  <content contentuid="hb56970bdg8455g4db7gaedcgfe8be2a6bacd" version="3">Eu disse a eles que cuidaria disso, que estava melhor equipado.</content>
  <content contentuid="hb610f816ga400g43d2g9e09gbf21f706cf3e" version="2">Não me questione. Eu sou o escolhido da Didade Absoluta.</content>
  <content contentuid="hbe5f3406g2429g4652g89fegc8109be441a2" version="1">&lt;i&gt;&lt;/i&gt;. Espero que seja capim-corvo, seu traidor!</content>
  <content contentuid="hc4b190a7g4357g4dd0g94cdgb86e2995385a" version="2">Sou um mercenário. Estou aqui para falar com meu chefe. Afaste-se imediatamente.</content>
  <content contentuid="hc7dc7cc3g4177g4a1dg8b27gd84693201344" version="5">Eu vi uma mulher. Ele me chamou de &quot;escolhido&quot;... E ele me curou.</content>
  <content contentuid="hca36759egd5c8g4189g8010g3ac582944f37" version="2">Não, eu não sou um mágico. Nem archi nem de qualquer tipo.</content>
  <content contentuid="hcabef0f9g8120g497bg9c69gc2a312ac92dd" version="2">Esperar. Não podemos falar sem ter que esfaquear o outro?</content>
  <content contentuid="hcfa5b63cg1b08g4a46gbc62gc28fc7a3031e" version="2">&lt;i&gt; [O padre] &lt;/i&gt;, bem? Você vai se ajoelhar antes do Escolhido de Boooal?</content>
  <content contentuid="hd0dc6a8cg7817g4177g9a40gb2d3d2d0b366" version="2">Com licença? Se há uma coisa que eu sou, é delicioso.</content>
  <content contentuid="hd459268dgdae2g4a77g9220g6ed2eb7eb7b8" version="2">Não sou um dos giths que atacaram a nave. Você sabe tudo sobre isso.</content>
  <content contentuid="hda559f74g446ag445eg99edg1750208f9a8c" version="2">Não quero ser rude, mas o que exatamente você é?</content>
  <content contentuid="hdbc96cc3g8dc7g44edgbb86g2f7c96834116" version="2">Se continuar escondendo coisas de mim, terei que repensar que estamos viajando juntos.</content>
  <content contentuid="he036c8f6gecb7g4622g9baagc0154cad0b94" version="2">Eu disse a ele que conhecia bem o joguinho dele. Eu mesmo tinha recorrido a ele em mais de uma ocasião.</content>
  <content contentuid="he1d0c35fg82fag4929ga4acgc682427ef9b9" version="2">Sou um guerreiro alienígena de outro plano de existência.</content>
  <content contentuid="he5428c33gbf68g420bg94f3gae62a2db23bf" version="4">Sobreviveremos juntos e ficaremos mais fortes.</content>
  <content contentuid="he62fc626gb016g44ccg86f3g95027191ceb1" version="2">Não sou um assassino.</content>
  <content contentuid="he78bd14fg4a48g4cb7g8270ga8a2a3e3de29" version="2">Eu me desculpei. Eu estava doente e o sono e a didade dela eram a minha melhor chance de permanecer vivo.</content>
  <content contentuid="he88eb2c2gc813g438agafccg5ca2d5dc4658" version="4">Essa &quot;didade&quot; foi fixada em nós. Tenho certeza que não combina conosco, não é?</content>
  <content contentuid="hea6c9617gcb84g4b4dg8d08g031fd03d1545" version="1">Bem, eu sou humano.</content>
  <content contentuid="hec6095c7g10e8g43c2g8218g2f937250b954" version="1">Eu não sou seu.</content>
  <content contentuid="hefbfeb02gc43fg46dbg8d83g518f9ebdf0be" version="2">Você parece surpreendentemente calmo. Minha aparência geralmente causa uma reação mais forte.</content>
  <content contentuid="hf11db015ga6afg442bg9c22g7ff3a48b8ac1" version="3">Não, eu não sou um mágico.</content>
  <content contentuid="hf2854058g3b18g4b3bg8139gbd922406da8b" version="3">Por que seria? Notamos muito do que fizeram conosco.</content>
  <content contentuid="hf3c8d39cg78dcg4218g8294g796397355f01" version="3">Você tem uma coisa dentro de você, também. Tenho certeza disso.</content>
  <content contentuid="hf3d1240cg4450g4627ga317g2605e3280032" version="1">Sim, um elfo do pântano.</content>
  <content contentuid="hf7888cc6gbbc0g4e29g9248gdeb6b3f72189" version="1">Você cometeu um erro. Isso não te faz mais fraco. Isso faz de você muito... Bem, não humano, mas você sabe o que quero dizer.</content>
  <content contentuid="hf7dcdba6g5506g46c8gb86agcfe89389848f" version="1">Formiga? Você está me chamando de canja?</content>
  <content contentuid="hf91b83abgee6cg4a02g9d71g5ef1c586eeb7" version="2">Sou muito melhor que mágico: sou feiticeira.</content>
  <content contentuid="hfb3d02b3g1b42g47d1g8cafg7e118db9c187" version="2">Eu sou um clériga. Deixe-me curá-lo.</content>
  <content contentuid="hfe0bd13fg4988g414cgab6fgbe527e725fd7" version="3">Não sou nojento ou destituído, mas sou um inimigo.</content>
  <content contentuid="hfe969ac6g3c00g4cdeg802bgcf937bfbfef6" version="2">Confirmo minha decisão: não viajaremos juntos.</content>
  <content contentuid="hfec25983gbbd6g4441gb051g933986d34a12" version="3">Sou um grande guerreiro. Você realmente quer jogar em uma luta?</content>
</contentList>